README.md
setup.py
extractacy/__init__.py
extractacy/extract.py
extractacy/test.py
extractacy.egg-info/PKG-INFO
extractacy.egg-info/SOURCES.txt
extractacy.egg-info/dependency_links.txt
extractacy.egg-info/requires.txt
extractacy.egg-info/top_level.txt