Metadata-Version: 2.1
Name: extractacy
Version: 1.0.0
Summary: A SpaCy pipeline object for extracting values that correspond to a named entity (e.g., birth dates, account numbers, or laboratory results)
Home-page: https://github.com/jenojp/extractacy
Author: Jeno Pizarro
Author-email: jenopizzaro@gmail.com
License: MIT
Keywords: nlp, spacy, SpaCy, NER, entity extraction, value extraction
Platform: UNKNOWN
Classifier: Intended Audience :: Science/Research
Classifier: Development Status :: 4 - Beta
Classifier: License :: OSI Approved :: MIT License
Classifier: Programming Language :: Python :: 3.6
Classifier: Programming Language :: Python :: 3.7
Classifier: Programming Language :: Python :: 3.8
Classifier: Topic :: Scientific/Engineering :: Artificial Intelligence
Classifier: Topic :: Scientific/Engineering :: Bio-Informatics
Requires-Python: >=3.6.0
